ajpy/__init__.py
ajpy/ajp.py
ajpy-0.0.5.dist-info/DESCRIPTION.rst
ajpy-0.0.5.dist-info/METADATA
ajpy-0.0.5.dist-info/RECORD
ajpy-0.0.5.dist-info/WHEEL
ajpy-0.0.5.dist-info/metadata.json
ajpy-0.0.5.dist-info/top_level.txt
