Metadata-Version: 1.1
Name: ajpy
Version: 0.0.5
Summary: AJP package crafting library
Home-page: https://github.com/hypn0s/AJPy/
Author: Julien Legras
Author-email: julien.legras@synacktiv.com
License: BSD
Download-URL: https://github.com/hypn0s/AJPy/archive/master.zip
Keywords: ajp,java,network
Platform: UNKNOWN
Classifier: Programming Language :: Python
Classifier: Development Status :: 3 - Alpha
Classifier: Environment :: Other Environment
Classifier: Intended Audience :: Developers
Classifier: License :: OSI Approved :: BSD License
Classifier: Operating System :: POSIX
Classifier: Topic :: Software Development :: Libraries :: Python Modules
Classifier: Topic :: Security
Classifier: Topic :: System :: Networking
